odoo/addons/hr_expense_advance_clearing_consolidation/README.rst
odoo/addons/hr_expense_advance_clearing_consolidation/__init__.py
odoo/addons/hr_expense_advance_clearing_consolidation/__manifest__.py
odoo/addons/hr_expense_advance_clearing_consolidation/i18n/hr_expense_advance_clearing_consolidation.pot
odoo/addons/hr_expense_advance_clearing_consolidation/i18n/it.po
odoo/addons/hr_expense_advance_clearing_consolidation/i18n/pt_BR.po
odoo/addons/hr_expense_advance_clearing_consolidation/models/__init__.py
odoo/addons/hr_expense_advance_clearing_consolidation/models/hr_expense_sheet.py
odoo/addons/hr_expense_advance_clearing_consolidation/readme/CONTRIBUTORS.rst
odoo/addons/hr_expense_advance_clearing_consolidation/readme/DESCRIPTION.rst
odoo/addons/hr_expense_advance_clearing_consolidation/readme/USAGE.rst
odoo/addons/hr_expense_advance_clearing_consolidation/static/description/icon.png
odoo/addons/hr_expense_advance_clearing_consolidation/static/description/index.html
odoo/addons/hr_expense_advance_clearing_consolidation/tests/__init__.py
odoo/addons/hr_expense_advance_clearing_consolidation/tests/test_hr_expense_advance_clearing_consolidation.py
odoo/addons/hr_expense_advance_clearing_consolidation/views/hr_expense_sheet_view.xml
odoo14_addon_hr_expense_advance_clearing_consolidation-14.0.1.0.1.dev1.dist-info/METADATA
odoo14_addon_hr_expense_advance_clearing_consolidation-14.0.1.0.1.dev1.dist-info/WHEEL
odoo14_addon_hr_expense_advance_clearing_consolidation-14.0.1.0.1.dev1.dist-info/top_level.txt
odoo14_addon_hr_expense_advance_clearing_consolidation-14.0.1.0.1.dev1.dist-info/RECORD
